bastok/blines.py
bastok/tlines.py
bastok/charset/__init__.py
bastok/charset/msx.py
bastok/cli/basdump.py
bastok/cli/blines.py
bastok/cli/detok.py
bastok/detok/msx2.py
binary/__init__.py
binary/memimage.py
binary/romimage.py
binary/symtab.py
binary/cli/msx_dasm.py
binary/cli/p2b.py
binary/tool/__init__.py
binary/tool/asl.py
binary/tool/asxxxx.py
cmtconv/analyze.py
cmtconv/audio.py
cmtconv/bytestream.py
cmtconv/formats.py
cmtconv/logging.py
cmtconv/cli/analyze_cmt.py
cmtconv/cli/cmtconv.py
cmtconv/platform/fm7.py
cmtconv/platform/jr200.py
cmtconv/platform/mb6885.py
cmtconv/platform/pc8001.py
cmtconv/platform/tk85.py
r8format-0.0.9.dist-info/METADATA
r8format-0.0.9.dist-info/WHEEL
r8format-0.0.9.dist-info/entry_points.txt
r8format-0.0.9.dist-info/top_level.txt
r8format-0.0.9.dist-info/RECORD
