Metadata-Version: 2.4
Name: r8format
Version: 0.0.9
Summary: Retrocomputing 8-bit file format manipulation tools
Author-email: "Curt J. Sampson" <cjs@cynic.net>, Stuart Croy <stuartcroy@mac.com>
Project-URL: homepage, https://github.com/mc68-net/t8dev/tree/main/r8format
Project-URL: source, https://github.com/mc68-net/t8dev
Project-URL: tracker, https://github.com/mc68-net/t8dev/issues
Requires-Python: >=3.6
